pyshell/__init__.py
pyshell/main.py
pyshell/commands/__init__.py
pyshell/commands/cat.py
pyshell/commands/cd.py
pyshell/commands/clear.py
pyshell/commands/cp.py
pyshell/commands/find.py
pyshell/commands/grep.py
pyshell/commands/head.py
pyshell/commands/ls.py
pyshell/commands/mkdir.py
pyshell/commands/mv.py
pyshell/commands/pwd.py
pyshell/commands/rm.py
pyshell/commands/rmdir.py
pyshell/commands/sizeof.py
pyshell/commands/tail.py
pyshell/core/__init__.py
pyshell/core/history.py
pyshell/core/pipeline_executor.py
pyshell/core/shell.py
pyshell/resources/demo_data.txt
pyshell/resources/test_file.txt
pyshell/tests/__init__.py
pyshell/tests/functional_tests/test_functional_workflows.py
pyshell/tests/unit_tests/test_cat_command.py
pyshell/tests/unit_tests/test_cd_command.py
pyshell/tests/unit_tests/test_clear_command.py
pyshell/tests/unit_tests/test_cp_command.py
pyshell/tests/unit_tests/test_file_ops.py
pyshell/tests/unit_tests/test_find_command.py
pyshell/tests/unit_tests/test_grep_command.py
pyshell/tests/unit_tests/test_head_command.py
pyshell/tests/unit_tests/test_helpers.py
pyshell/tests/unit_tests/test_history.py
pyshell/tests/unit_tests/test_ls_command.py
pyshell/tests/unit_tests/test_mkdir_command.py
pyshell/tests/unit_tests/test_mv_command.py
pyshell/tests/unit_tests/test_parsers.py
pyshell/tests/unit_tests/test_pipeline_executor.py
pyshell/tests/unit_tests/test_pwd_command.py
pyshell/tests/unit_tests/test_rm_command.py
pyshell/tests/unit_tests/test_rmdir_command.py
pyshell/tests/unit_tests/test_shell.py
pyshell/tests/unit_tests/test_sizeof_command.py
pyshell/tests/unit_tests/test_tail_command.py
pyshell/utils/__init__.py
pyshell/utils/file_ops.py
pyshell/utils/helpers.py
pyshell/utils/parsers.py
pyshell_cli_py5-1.0.0.dist-info/licenses/LICENSE
pyshell_cli_py5-1.0.0.dist-info/METADATA
pyshell_cli_py5-1.0.0.dist-info/WHEEL
pyshell_cli_py5-1.0.0.dist-info/entry_points.txt
pyshell_cli_py5-1.0.0.dist-info/top_level.txt
pyshell_cli_py5-1.0.0.dist-info/RECORD
