Metadata-Version: 2.4
Name: pyshell-cli-PY5
Version: 1.0.0
Summary: A modular UNIX-like shell implementation in Python with plugin architecture
Home-page: https://github.com/yourusername/pyshell
Author: PyShell Contributors-PrachiY,KetakiD,Deekshita
Author-email: PyShell Contributors <pyshell@example.com>
License: MIT
Project-URL: Homepage, https://github.com/yourusername/pyshell
Project-URL: Repository, https://github.com/yourusername/pyshell
Project-URL: Issues, https://github.com/yourusername/pyshell/issues
Project-URL: Documentation, https://github.com/yourusername/pyshell/blob/main/README.md
Keywords: shell,terminal,command-line,unix,bash,cli,educational
Classifier: Development Status :: 4 - Beta
Classifier: Intended Audience :: Developers
Classifier: Intended Audience :: Education
Classifier: Topic :: System :: Shells
Classifier: Topic :: Education
Classifier: License :: OSI Approved :: MIT License
Classifier: Programming Language :: Python :: 3
Classifier: Programming Language :: Python :: 3.7
Classifier: Programming Language :: Python :: 3.8
Classifier: Programming Language :: Python :: 3.9
Classifier: Programming Language :: Python :: 3.10
Classifier: Programming Language :: Python :: 3.11
Classifier: Programming Language :: Python :: 3.12
Classifier: Programming Language :: Python :: 3.13
Classifier: Operating System :: OS Independent
Requires-Python: >=3.7
License-File: LICENSE
Dynamic: author
Dynamic: home-page
Dynamic: license-file
Dynamic: requires-python
